<!DOCTYPE ui:UiBinder SYSTEM "http://dl.google.com/gwt/DTD/xhtml.ent">
<ui:UiBinder xmlns:ui="urn:ui:com.google.gwt.uibinder"
             xmlns:c="urn:import:stroom.widget.customdatebox.client"
             xmlns:g="urn:import:com.google.gwt.user.client.ui"
             xmlns:b="urn:import:stroom.widget.button.client"
             xmlns:tickbox="urn:import:stroom.widget.tickbox.client.view"
             xmlns:item="urn:import:stroom.item.client"
             xmlns:v="urn:import:stroom.widget.dropdowntree.client.view"
             xmlns:form="urn:import:stroom.widget.form.client">
    <g:FlowPanel styleName="max dock-container-vertical form">
        <form:FormGroup identity="owner" label="Owner">
            <g:FlowPanel styleName="max dock-container-vertical">
                <g:Label ui:field="ownerLabel" addStyleNames="w-100"/>
                <item:SelectionBox ui:field="ownerSelectionBox" addStyleNames="w-100"/>
            </g:FlowPanel>
        </form:FormGroup>
        <form:FormGroup identity="name" label="API Key Name">
            <g:TextBox ui:field="nameTextBox" addStyleNames="w-100"/>
        </form:FormGroup>
        <form:FormGroup ui:field="prefixFormGroup" identity="prefix" label="API Key Prefix">
            <g:TextBox ui:field="prefixTextBox" addStyleNames="w-100"/>
        </form:FormGroup>
        <form:FormGroup ui:field="apiKeyFormGroup" identity="apiKey" label="API Key (you must copy this)">
            <g:FlowPanel styleName="max dock-container-vertical">
                <g:TextArea ui:field="apiKeyTextArea" addStyleNames="w-100"/>
                <g:FlowPanel styleName="max dock-container-horizontal align-center">
                    <b:ButtonPanel ui:field="apiKeyButtonPanel" />
                    <g:Label ui:field="copyToClipboardLabel" />
                </g:FlowPanel>
            </g:FlowPanel>
        </form:FormGroup>
        <form:FormGroup identity="enabled" label="Enabled">
            <tickbox:CustomCheckBox ui:field="enabledCheckBox" identity="enabledCheckBox" label="Enabled"/>
        </form:FormGroup>
        <form:FormGroup identity="comments" label="Comments">
            <g:TextArea ui:field="commentsTextArea" addStyleNames="w-100"/>
        </form:FormGroup>
        <form:FormGroup identity="expiry" label="Expiry Date">
            <c:MyDateBox ui:field="expiresOnDateBox" addStyleNames="w-100"/>
        </form:FormGroup>
    </g:FlowPanel>
</ui:UiBinder>
